RapidHtml2Pdf/__init__.py
RapidHtml2Pdf/assets.py
RapidHtml2Pdf/cli.py
RapidHtml2Pdf/converter.py
RapidHtml2Pdf/exceptions.py
RapidHtml2Pdf/renderer.py
rapidhtml2pdf-1.0.0.dist-info/licenses/LICENSE
rapidhtml2pdf-1.0.0.dist-info/METADATA
rapidhtml2pdf-1.0.0.dist-info/WHEEL
rapidhtml2pdf-1.0.0.dist-info/top_level.txt
rapidhtml2pdf-1.0.0.dist-info/RECORD
