Metadata-Version: 2.4
Name: RapidHtml2Pdf
Version: 1.0.0
Summary: Convert HTML (with CSS, SCSS, icons, and images) to PDF with async/threaded support
Home-page: https://github.com/Xyhercode/RapidHtml2Pdf
Author: Rakesh Sharma
Author-email: Rakesh Sharma <rakeshsharmanine@gmail.com>
License: MIT
Project-URL: Homepage, https://github.com/Xyhercode/RapidHtml2Pdf
Project-URL: Repository, https://github.com/Xyhercode/RapidHtml2Pdf
Classifier: Development Status :: 3 - Alpha
Classifier: Intended Audience :: Developers
Classifier: Topic :: Text Processing :: Markup :: HTML
Classifier: License :: OSI Approved :: MIT License
Classifier: Programming Language :: Python :: 3
Requires-Python: >=3.8
License-File: LICENSE
Requires-Dist: beautifulsoup4>=4.12
Requires-Dist: aiohttp>=3.9
Requires-Dist: aiofiles>=23.2
Requires-Dist: typer>=0.9
Requires-Dist: playwright>=1.41
Requires-Dist: libsass>=0.22
Requires-Dist: weasyprint>=61.0
Requires-Dist: reportlab>=4.0
Dynamic: license-file
